websocket_communication_server/__init__.py
websocket_communication_server/connection.py
websocket_communication_server/messagetemplates.py
websocket_communication_server/ping_pong_example.py
websocket_communication_server/socketclient.py
websocket_communication_server/socketserver.py
websocket_communication_server/www_data/__init__.py
websocket_communication_server/www_data/websocket_communication_server.js
WsComSrv-0.1.1555408076.dist-info/LICENSE.txt
WsComSrv-0.1.1555408076.dist-info/METADATA
WsComSrv-0.1.1555408076.dist-info/WHEEL
WsComSrv-0.1.1555408076.dist-info/top_level.txt
WsComSrv-0.1.1555408076.dist-info/RECORD
