Metadata-Version: 2.1
Name: WsComSrv
Version: 0.1.1555408076
Summary: A basic websocket communication server
Home-page: https://github.com/JulianKimmig/websocket_communication_server
Author: Julian Kimmig
Author-email: julian-kimmig@gmx.net
License: UNKNOWN
Platform: UNKNOWN
Classifier: Programming Language :: Python :: 3
Classifier: License :: OSI Approved :: MIT License
Classifier: Operating System :: OS Independent
Requires-Dist: FilterDict
Requires-Dist: websocket-client
Requires-Dist: websockets
